lolacli/__init__.py
lolacli/apps.txt
lolacli/install.sh
lolacli/lolacli.py
lolacli-0.2.4.dist-info/entry_points.txt
lolacli-0.2.4.dist-info/LICENSE
lolacli-0.2.4.dist-info/WHEEL
lolacli-0.2.4.dist-info/METADATA
lolacli-0.2.4.dist-info/RECORD
